Workbook

Sheet Read Me
A1: Freelance Rate Card & Finance Tracker
A3: A blank kit. Fill in the yellow cells and the math updates itself.
A5: Tabs:
A6: Rate Card set your hourly rate, get a price per project type
A7: Subscriptions track tool costs: active vs. fully-loaded vs. max tier
A8: Ledger one row per transaction, split into income / expense types
A9: Quarterly auto-totals the ledger by quarter and sets aside for tax
A11: Legend:
A12: Yellow cell = an input you edit
A13: Blue text = a starting/example value; overwrite it
A14: Black text = a formula; leave it alone, it recalculates
A16: Each table has one example row in blue. Replace it with your own.
... A18: advice. Confirm your own numbers with a professional.

Sheet Rate Card
A1: Rate Card
A2: Price = min hours x your hourly rate. Adjust the hour anchors to your own pace.
A4: Hourly rate ($/hr) | B4: 100
A5: Full-time conversion ($/yr) | B5: 150000
A7: Design type | B7: Min hours (est.) | C7: Price
A8: Presentations, decks | B8: 5 | C8: =B8*$B$4 -> 500
A9: Emails, broadcast | B9: 5 | C9: =B9*$B$4 -> 500
A10: Consult | B10: 10 | C10: =B10*$B$4 -> 1000
A11: Print, packaging, production | B11: 15 | C11: =B11*$B$4 -> 1500
A12: Single page / landing-page UI | B12: 50 | C12: =B12*$B$4 -> 5000
A13: Full site UX/UI | B13: 100 | C13: =B13*$B$4 -> 10000
A14: Experiential | B14: 150 | C14: =B14*$B$4 -> 15000

Sheet Subscriptions
A1: Pro Subscriptions / mo
A2: Active = today. Prospective = fully-loaded stack. Maximum = tool's top tier.
A4: Tool | B4: Active | C4: Prospective | D4: Difference | E4: Maximum
A5: Email / domain | B5: 12 | C5: 12 | D5: =C5-B5 -> 0 | E5: 20
A6: Office suite | D6: =C6-B6 -> 0
A7: Cloud storage | D7: =C7-B7 -> 0
A8: Adobe Creative Cloud | D8: =C8-B8 -> 0
A9: Figma | D9: =C9-B9 -> 0
A10: LinkedIn | D10: =C10-B10 -> 0
A11: AI assistant | D11: =C11-B11 -> 0
A12: Time tracking | D12: =C12-B12 -> 0
A13: Whiteboard / collaboration | D13: =C13-B13 -> 0
A14: Total | B14: =SUM(B5:B13) -> 12 | C14: =SUM(C5:C13) -> 12 | D14: =SUM(D5:D13) -> 0 | E14: =SUM(E5:E13) -> 20

Sheet Ledger
A1: Income & Expense Ledger
A2: Date | B2: Description | C2: Income (+) | D2: Software (-) | E2: Equipment (-) | F2: Other (-) | G2: Notes
A3: 46068 | B3: Client A retainer (example) | C3: 2000 | G3: ACH / invoice #
A4: 46091 | B4: Cloud storage (example) | D4: 12 | G4: monthly subscription
A5: 46162 | B5: New laptop (example) | E5: 1800 | G5: equipment

Sheet Quarterly
A1: Quarterly Roll-up
A3: Year | B3: 2026
A4: Set-aside rate | B4: 0.3
A6: Quarter | B6: Gross income | C6: Total expenses | D6: Net profit | E6: Set aside
A7: Q1 (Jan-Mar) | B7: =SUMIFS(Ledger!$C:$C,Ledger!$A:$A,">="&DATE($B$3,1,1),Ledger!$A:$A,"<="&DATE($B$3,3,31)) -> 2000 | C7: =SUMIFS(Ledger!$D:$D,Ledger!$A:$A,">="&DATE($B$3,1,1),Ledger!$A:$A,"<="&DATE($B$3,3,31))+SUMIFS(Ledger!$E:$E,Ledger!$A:$A,">="&DATE($B$3,1,1),Ledger!$A:$A,"<="&DATE($B$3,3,31))+SUMIFS(Ledger!$F:$F,Ledger!$A:$A,">="&DATE($B$3,1,1),Ledger!$A:$A,"<="&DATE($B$3,3,31)) -> 12 | D7: =B7-C7 -> 1988 | E7: =D7*$B$4 -> 596.4
A8: Q2 (Apr-Jun) | B8: =SUMIFS(Ledger!$C:$C,Ledger!$A:$A,">="&DATE($B$3,4,1),Ledger!$A:$A,"<="&DATE($B$3,6,30)) -> 0 | C8: =SUMIFS(Ledger!$D:$D,Ledger!$A:$A,">="&DATE($B$3,4,1),Ledger!$A:$A,"<="&DATE($B$3,6,30))+SUMIFS(Ledger!$E:$E,Ledger!$A:$A,">="&DATE($B$3,4,1),Ledger!$A:$A,"<="&DATE($B$3,6,30))+SUMIFS(Ledger!$F:$F,Ledger!$A:$A,">="&DATE($B$3,4,1),Ledger!$A:$A,"<="&DATE($B$3,6,30)) -> 1800 | D8: =B8-C8 -> -1800 | E8: =D8*$B$4 -> -540
A9: Q3 (Jul-Sep) | B9: =SUMIFS(Ledger!$C:$C,Ledger!$A:$A,">="&DATE($B$3,7,1),Ledger!$A:$A,"<="&DATE($B$3,9,30)) -> 0 | C9: =SUMIFS(Ledger!$D:$D,Ledger!$A:$A,">="&DATE($B$3,7,1),Ledger!$A:$A,"<="&DATE($B$3,9,30))+SUMIFS(Ledger!$E:$E,Ledger!$A:$A,">="&DATE($B$3,7,1),Ledger!$A:$A,"<="&DATE($B$3,9,30))+SUMIFS(Ledger!$F:$F,Ledger!$A:$A,">="&DATE($B$3,7,1),Ledger!$A:$A,"<="&DATE($B$3,9,30)) -> 0 | D9: =B9-C9 -> 0 | E9: =D9*$B$4 -> 0
A10: Q4 (Oct-Dec) | B10: =SUMIFS(Ledger!$C:$C,Ledger!$A:$A,">="&DATE($B$3,10,1),Ledger!$A:$A,"<="&DATE($B$3,12,31)) -> 0 | C10: =SUMIFS(Ledger!$D:$D,Ledger!$A:$A,">="&DATE($B$3,10,1),Ledger!$A:$A,"<="&DATE($B$3,12,31))+SUMIFS(Ledger!$E:$E,Ledger!$A:$A,">="&DATE($B$3,10,1),Ledger!$A:$A,"<="&DATE($B$3,12,31))+SUMIFS(Ledger!$F:$F,Ledger!$A:$A,">="&DATE($B$3,10,1),Ledger!$A:$A,"<="&DATE($B$3,12,31)) -> 0 | D10: =B10-C10 -> 0 | E10: =D10*$B$4 -> 0
A11: Year | B11: =SUM(B7:B10) -> 2000 | C11: =SUM(C7:C10) -> 1812 | D11: =SUM(D7:D10) -> 188 | E11: =SUM(E7:E10) -> 56.4
